[
  {
    "id": "jobspy_5078147661690685740",
    "title": "BAS Designer",
    "company": "Ainsworth Inc",
    "location": "Calgary, Alberta, Canada",
    "source": "Linkedin",
    "url": "https://www.linkedin.com/jobs/view/4085227089",
    "date": "nan",
    "description": "**If you thrive in a team\\-oriented workplace that challenges your skills, to drive your career development, embraces diversity and rewards innovation, with competitive pay and great employee programs, join the GDI Ainsworth** \n**team today!**\n**Job Summary**\n We are currently looking for an Controls Designer\n **Level 1** \n to join our growing team based out of Calgary Alberta. As an\n **Controls Designer Level 1** \n you will be involved in the installation, commissioning and servicing of commerc",
    "scraped_at": "2026-03-08T20:45:32.363310"
  },
  {
    "id": "linkedin_1484715331657606047",
    "title": "BAS Designer",
    "company": "Ainsworth Inc",
    "location": "Calgary, Alberta, Canada",
    "source": "LinkedIn",
    "url": "https://ca.linkedin.com/jobs/view/bas-designer-at-ainsworth-inc-4085227089",
    "date": "2026-03-08",
    "description": "",
    "scraped_at": "2026-03-08T20:45:32.770272"
  }
]